kulfi/__init__.py
kulfi-0.0.1.dist-info/METADATA
kulfi-0.0.1.dist-info/WHEEL
kulfi-0.0.1.dist-info/licenses/LICENSE
kulfi-0.0.1.dist-info/RECORD
